pyenv_load/__init__.py
pyenv_load/core.py
pyenv_load-0.1.1.dist-info/LICENSE
pyenv_load-0.1.1.dist-info/METADATA
pyenv_load-0.1.1.dist-info/WHEEL
pyenv_load-0.1.1.dist-info/RECORD
