Metadata-Version: 2.3
Name: pyenv-load
Version: 0.1.1
Summary: Loads from text or JSON file into environment
License: MIT
Keywords: environment,variables,env,dotenv,json,configuration
Author: Adam Gogacz
Author-email: adam.byk.360@gmail.com
Requires-Python: >=3.9
Classifier: Development Status :: 4 - Beta
Classifier: Intended Audience :: Developers
Classifier: License :: OSI Approved :: MIT License
Classifier: Programming Language :: Python :: 3
Classifier: Programming Language :: Python :: 3.10
Classifier: Programming Language :: Python :: 3.11
Classifier: Programming Language :: Python :: 3.12
Classifier: Programming Language :: Python :: 3.13
Classifier: Topic :: Software Development :: Libraries :: Python Modules
Classifier: Topic :: Utilities
